lib_calculator/__init__.py
lib_calculator-0.0.1.dist-info/LICENCE.txt
lib_calculator-0.0.1.dist-info/METADATA
lib_calculator-0.0.1.dist-info/WHEEL
lib_calculator-0.0.1.dist-info/top_level.txt
lib_calculator-0.0.1.dist-info/RECORD
