Metadata-Version: 2.1
Name: lib-calculator
Version: 0.0.1
Summary: A very simple calculator
Home-page: UNKNOWN
Author: mohammed Almamari
Author-email: mohm104002@gmail.org
License: MIT
Keywords: calculator
Platform: UNKNOWN
Classifier: Development Status :: 5 - Production/Stable
Classifier: Intended Audience :: Education
Classifier: Operating System :: Microsoft :: Windows :: Windows 10
Classifier: License :: OSI Approved :: MIT License
Classifier: Programming Language :: Python :: 3
License-File: LICENCE.txt
